pyikaild/__init__.py
pyikaild/ika.py
pyikaild/ild.py
pyikaild/processing.py
pyikaild-0.0.6.dist-info/METADATA
pyikaild-0.0.6.dist-info/WHEEL
pyikaild-0.0.6.dist-info/RECORD
