Metadata-Version: 2.3
Name: pyikaild
Version: 0.0.6
Summary: Improved K-Anonymity and l-Diversity library
License: MIT
Keywords: anonymization,anonymization evaluation,privacy,data privacy,data anonymization,data privacy evaluation
Author: woaitsAryan
Author-email: yoprince.ab@gmail.com
Requires-Python: >=3.12,<4.0
Classifier: License :: OSI Approved :: MIT License
Classifier: Programming Language :: Python :: 3
Classifier: Programming Language :: Python :: 3.12
Classifier: Programming Language :: Python :: 3.13
Classifier: Programming Language :: Python :: 3.11
Provides-Extra: lint
Provides-Extra: test
Requires-Dist: anonpy (>=1.0.0,<2.0.0)
Requires-Dist: anonypy (>=0.2.1,<0.3.0)
Requires-Dist: build (>=1.2.2.post1,<2.0.0)
Requires-Dist: pandas (>=2.2.3,<3.0.0)
Requires-Dist: pandas-stubs (>=2.2.3.250308,<3.0.0.0)
Requires-Dist: pydocstyle (>=6.3.0,<7.0.0)
